Metadata-Version: 1.1
Name: coder
Version: 1.0.6
Summary: A graphical interface tool, integrated web encoding/decoding method, hash method and the ASCII table.
Home-page: https://github.com/emptyxl/coder
Author: empty_xl
Author-email: empty_xl@163.com
License: MIT
Keywords: encdoer decoder encoding decoding
Platform: UNKNOWN
Classifier: Development Status :: 4 - Beta
Classifier: License :: OSI Approved :: MIT License
Classifier: Topic :: Utilities
